vampgui/__init__.py
vampgui/background.png
vampgui/cif_2_ucf.py
vampgui/file_io.py
vampgui/helpkey.py
vampgui/home_page.py
vampgui/input_file.py
vampgui/logo.png
vampgui/logo1.png
vampgui/main.py
vampgui/material.py
vampgui/plot_output.py
vampgui/theme.py
vampgui/ufc_file.py
vampgui/vam.ico
vampgui/vampire_console.py
vampgui/vampire_pymatgen.py
vampgui/version.py
vampgui/visualization.py
vampgui-2.2.4.dist-info/METADATA
vampgui-2.2.4.dist-info/WHEEL
vampgui-2.2.4.dist-info/entry_points.txt
vampgui-2.2.4.dist-info/top_level.txt
vampgui-2.2.4.dist-info/RECORD
