Metadata-Version: 2.1
Name: vampgui
Version: 2.2.4
Summary: Graphical interface for VAMPIRE: Atomistic simulation of magnetic materials.
Home-page: https://github.com/ghlam14/vampgui/tree/main
Author: G. Benabdellah
Author-email: ghlam.benabdellah@gmail.com
Classifier: Programming Language :: Python :: 3
Classifier: Programming Language :: Python :: 3.8
Classifier: License :: OSI Approved :: GNU General Public License v3 (GPLv3)
Classifier: Operating System :: OS Independent
Requires-Python: >=3.8
Requires-Dist: Pillow >=10.0.0
Requires-Dist: matplotlib >=3.7.5
Requires-Dist: numpy >=1.24.4
Requires-Dist: pymatgen >=2023.8.10
